<?xml version="1.0" encoding="UTF-8" standalone="yes"?>
<root>
      <data missionId="1" quality="1" weight="540" baseAward="30000_1780035_5,30000_840420_5" advAward="30000_840162_15,30000_800109_2" baseCondition="1_2000" advCondition="5_1_1_1008,6_1_3101001_1" continueTime="3600" />
      <data missionId="2" quality="2" weight="480" baseAward="30000_1780035_10,30000_840420_10" advAward="30000_840162_30,30000_1000002_2" baseCondition="1_4000" advCondition="5_1_1_1017,5_1_1_1008" continueTime="7200" />
      <data missionId="3" quality="3" weight="120" baseAward="30000_1780035_15,30000_840420_15" advAward="30000_840162_50,30000_1000002_4" baseCondition="1_6000" advCondition="5_1_2_1002,6_1_3101011_1" continueTime="14400" />
      <data missionId="4" quality="4" weight="30" baseAward="30000_1780035_20,30000_840420_20" advAward="30000_840162_75,30000_1000002_10" baseCondition="1_8000" advCondition="5_1_4_1002,5_1_4_1017" continueTime="28800" />
      <data missionId="5" quality="1" weight="360" baseAward="30000_1780035_5,30000_840420_5" advAward="30000_840162_15,30000_800109_2" baseCondition="1_1500" advCondition="5_1_1_1005,6_1_3101047_1" continueTime="3600" />
      <data missionId="6" quality="2" weight="320" baseAward="30000_1780035_10,30000_840420_10" advAward="30000_840162_30,30000_1000002_2" baseCondition="1_3000" advCondition="5_1_1_1001,5_1_1_1005" continueTime="7200" />
      <data missionId="7" quality="3" weight="80" baseAward="30000_1780035_15,30000_840420_15" advAward="30000_840162_50,30000_1000002_4" baseCondition="1_4500" advCondition="5_1_2_1001,5_1_3_1005" continueTime="14400" />
      <data missionId="8" quality="4" weight="20" baseAward="30000_1780035_20,30000_840420_20" advAward="30000_840162_75,30000_1000002_10" baseCondition="1_6000" advCondition="5_1_3_1001,6_1_3101030_1" continueTime="28800" />
      <data missionId="9" quality="1" weight="270" baseAward="30000_1780035_5,30000_840420_5" advAward="30000_840162_15,30000_800109_2" baseCondition="1_2000" advCondition="5_1_1_1006,6_1_3101003_1" continueTime="3600" />
      <data missionId="10" quality="2" weight="240" baseAward="30000_1780035_10,30000_840420_10" advAward="30000_840162_30,30000_1000002_2" baseCondition="1_4000" advCondition="5_1_1_1020,5_1_1_1006" continueTime="7200" />
      <data missionId="11" quality="3" weight="60" baseAward="30000_1780035_15,30000_840420_15" advAward="30000_840162_50,30000_1000002_4" baseCondition="1_6000" advCondition="5_1_2_1020,6_1_3101029_1" continueTime="14400" />
      <data missionId="12" quality="4" weight="15" baseAward="30000_1780035_20,30000_840420_20" advAward="30000_840162_75,30000_1000002_10" baseCondition="1_8000" advCondition="5_1_3_1020,5_1_4_1006" continueTime="28800" />
      <data missionId="13" quality="1" weight="270" baseAward="30000_1780035_5,30000_840420_5" advAward="30000_840162_15,30000_800109_2" baseCondition="1_2000" advCondition="5_1_1_1010,6_1_3101005_1" continueTime="3600" />
      <data missionId="14" quality="2" weight="240" baseAward="30000_1780035_10,30000_840420_10" advAward="30000_840162_30,30000_1000002_2" baseCondition="1_4000" advCondition="5_1_1_1018,5_1_1_1010" continueTime="7200" />
      <data missionId="15" quality="3" weight="60" baseAward="30000_1780035_15,30000_840420_15" advAward="30000_840162_50,30000_1000002_4" baseCondition="1_6000" advCondition="5_1_2_1018,6_1_3101055_1" continueTime="14400" />
      <data missionId="16" quality="4" weight="15" baseAward="30000_1780035_20,30000_840420_20" advAward="30000_840162_75,30000_1000002_10" baseCondition="1_8000" advCondition="5_1_3_1018,5_1_4_1010" continueTime="28800" />
      <data missionId="17" quality="1" weight="270" baseAward="30000_1780035_5,30000_840420_5" advAward="30000_840162_15,30000_800109_2" baseCondition="1_2000" advCondition="5_1_1_1009,6_1_3101053_1" continueTime="3600" />
      <data missionId="18" quality="2" weight="240" baseAward="30000_1780035_10,30000_840420_10" advAward="30000_840162_30,30000_1000002_2" baseCondition="1_4000" advCondition="5_1_2_1009,6_1_3101007_1" continueTime="7200" />
      <data missionId="19" quality="3" weight="60" baseAward="30000_1780035_15,30000_840420_15" advAward="30000_840162_50,30000_1000002_4" baseCondition="1_6000" advCondition="5_1_1_1035,4_100_1_1" continueTime="14400" />
      <data missionId="20" quality="4" weight="15" baseAward="30000_1780035_20,30000_840420_20" advAward="30000_840162_75,30000_1000002_10" baseCondition="1_8000" advCondition="5_1_2_1035,6_1_3101057_1" continueTime="28800" />
      <data missionId="21" quality="1" weight="180" baseAward="30000_1780035_5,30000_840420_5" advAward="30000_840162_15,30000_800109_2" baseCondition="1_2000" advCondition="5_1_1_1021,6_1_3101017_1" continueTime="3600" />
      <data missionId="22" quality="2" weight="160" baseAward="30000_1780035_10,30000_840420_10" advAward="30000_840162_30,30000_1000002_2" baseCondition="1_4000" advCondition="5_1_1_1037,4_60_1_2" continueTime="7200" />
      <data missionId="23" quality="3" weight="40" baseAward="30000_1780035_15,30000_840420_15" advAward="30000_840162_50,30000_1000002_4" baseCondition="1_6000" advCondition="5_1_1_1042,4_80_1_2" continueTime="14400" />
      <data missionId="24" quality="4" weight="20" baseAward="30000_1780035_20,30000_840420_20" advAward="30000_840162_75,30000_1000002_10" baseCondition="1_8000" advCondition="5_1_1_1004,4_100_1_2" continueTime="28800" />
      <data missionId="25" quality="1" weight="360" baseAward="30000_1780035_5,30000_840420_5" advAward="30000_840162_15,30000_800109_2" baseCondition="2_1500" advCondition="5_1_1_1029,6_1_3102008_1" continueTime="3600" />
      <data missionId="26" quality="2" weight="320" baseAward="30000_1780035_10,30000_840420_10" advAward="30000_840162_30,30000_1000002_2" baseCondition="2_3000" advCondition="5_1_1_1028,5_1_3_1029" continueTime="7200" />
      <data missionId="27" quality="3" weight="80" baseAward="30000_1780035_15,30000_840420_15" advAward="30000_840162_50,30000_1000002_4" baseCondition="2_4500" advCondition="5_1_3_1028,4_80_1_2" continueTime="14400" />
      <data missionId="28" quality="4" weight="40" baseAward="30000_1780035_20,30000_840420_20" advAward="30000_840162_75,30000_1000002_10" baseCondition="2_6000" advCondition="5_1_5_1028,4_100_1_2" continueTime="28800" />
      <data missionId="29" quality="1" weight="360" baseAward="30000_1780035_5,30000_840420_5" advAward="30000_840162_15,30000_800109_2" baseCondition="3_2000" advCondition="5_1_1_1025,5_1_1_1026" continueTime="3600" />
      <data missionId="30" quality="2" weight="320" baseAward="30000_1780035_10,30000_840420_10" advAward="30000_840162_30,30000_1000002_2" baseCondition="3_4000" advCondition="5_1_3_1025,5_1_2_1026" continueTime="7200" />
      <data missionId="31" quality="3" weight="80" baseAward="30000_1780035_15,30000_840420_15" advAward="30000_840162_50,30000_1000002_4" baseCondition="3_6000" advCondition="5_1_4_1025,5_1_3_1026" continueTime="14400" />
      <data missionId="32" quality="4" weight="40" baseAward="30000_1780035_20,30000_840420_20" advAward="30000_840162_75,30000_1000002_10" baseCondition="3_8000" advCondition="5_1_3_1003,5_1_5_1025" continueTime="28800" />
      <data missionId="33" quality="1" weight="180" baseAward="30000_1780035_5,30000_840420_5" advAward="30000_840162_15,30000_800109_2" baseCondition="2_1500" advCondition="5_1_1_1023,6_1_3102004_1" continueTime="3600" />
      <data missionId="34" quality="2" weight="160" baseAward="30000_1780035_10,30000_840420_10" advAward="30000_840162_30,30000_1000002_2" baseCondition="2_3000" advCondition="5_1_2_1023,5_1_1_1027" continueTime="7200" />
      <data missionId="35" quality="3" weight="40" baseAward="30000_1780035_15,30000_840420_15" advAward="30000_840162_50,30000_1000002_4" baseCondition="2_4500" advCondition="5_1_3_1023,5_1_2_1027" continueTime="14400" />
      <data missionId="36" quality="4" weight="20" baseAward="30000_1780035_20,30000_840420_20" advAward="30000_840162_75,30000_1000002_10" baseCondition="2_6000" advCondition="5_1_4_1023,5_1_3_1027" continueTime="28800" />
      <data missionId="37" quality="1" weight="360" baseAward="30000_1780035_5,30000_840420_5" advAward="30000_840162_15,30000_800109_2" baseCondition="3_2000" advCondition="5_1_1_1022,6_1_3103018_1" continueTime="3600" />
      <data missionId="38" quality="2" weight="320" baseAward="30000_1780035_10,30000_840420_10" advAward="30000_840162_30,30000_1000002_2" baseCondition="3_4000" advCondition="5_1_2_1022,5_1_2_1024" continueTime="7200" />
      <data missionId="39" quality="3" weight="80" baseAward="30000_1780035_15,30000_840420_15" advAward="30000_840162_50,30000_1000002_4" baseCondition="3_6000" advCondition="5_1_3_1022,5_1_3_1024" continueTime="14400" />
      <data missionId="40" quality="4" weight="20" baseAward="30000_1780035_20,30000_840420_20" advAward="30000_840162_75,30000_1000002_10" baseCondition="3_8000" advCondition="5_1_4_1022,5_1_4_1024" continueTime="28800" />
      <data missionId="41" quality="1" weight="180" baseAward="30000_1780035_5,30000_840420_5" advAward="30000_840162_15,30000_800109_2" baseCondition="1_2500" advCondition="4_1_4_1,4_40_1_2" continueTime="3600" />
      <data missionId="42" quality="2" weight="160" baseAward="30000_1780035_10,30000_840420_10" advAward="30000_840162_30,30000_1000002_2" baseCondition="1_5000" advCondition="4_1_4_2,4_60_1_2" continueTime="7200" />
      <data missionId="43" quality="3" weight="40" baseAward="30000_1780035_15,30000_840420_15" advAward="30000_840162_50,30000_1000002_4" baseCondition="1_7500" advCondition="4_1_5_1,4_80_1_2" continueTime="14400" />
      <data missionId="44" quality="4" weight="20" baseAward="30000_1780035_20,30000_840420_20" advAward="30000_840162_75,30000_1000002_10" baseCondition="1_10000" advCondition="4_1_5_2,4_120_1_2" continueTime="28800" />
      <data missionId="45" quality="1" weight="180" baseAward="30000_1780035_5,30000_840420_5" advAward="30000_840162_15,30000_800109_2" baseCondition="2_2000" advCondition="4_1_4_1,4_40_1_2" continueTime="3600" />
      <data missionId="46" quality="2" weight="160" baseAward="30000_1780035_10,30000_840420_10" advAward="30000_840162_30,30000_1000002_2" baseCondition="2_4000" advCondition="4_1_4_1,4_60_1_2" continueTime="7200" />
      <data missionId="47" quality="3" weight="40" baseAward="30000_1780035_15,30000_840420_15" advAward="30000_840162_50,30000_1000002_4" baseCondition="2_6000" advCondition="4_1_4_2,4_80_1_2" continueTime="14400" />
      <data missionId="48" quality="4" weight="20" baseAward="30000_1780035_20,30000_840420_20" advAward="30000_840162_75,30000_1000002_10" baseCondition="2_8000" advCondition="4_1_4_2,4_120_1_2" continueTime="28800" />
      <data missionId="49" quality="1" weight="180" baseAward="30000_1780035_5,30000_840420_5" advAward="30000_840162_15,30000_800109_2" baseCondition="3_2000" advCondition="4_1_4_1,4_40_1_2" continueTime="3600" />
      <data missionId="50" quality="2" weight="160" baseAward="30000_1780035_10,30000_840420_10" advAward="30000_840162_30,30000_1000002_2" baseCondition="3_4000" advCondition="4_1_4_1,4_60_1_2" continueTime="7200" />
      <data missionId="51" quality="3" weight="40" baseAward="30000_1780035_15,30000_840420_15" advAward="30000_840162_50,30000_1000002_4" baseCondition="3_6000" advCondition="4_1_4_2,4_80_1_2" continueTime="14400" />
      <data missionId="52" quality="4" weight="20" baseAward="30000_1780035_20,30000_840420_20" advAward="30000_840162_75,30000_1000002_10" baseCondition="3_8000" advCondition="4_1_4_2,4_120_1_2" continueTime="28800" />
      <data missionId="53" quality="3" weight="40" baseAward="30000_1780035_15,30000_840420_15" advAward="30000_840162_50,30000_1000002_4" baseCondition="1_6000" advCondition="5_1_1_1049,6_1_3101054_1" continueTime="14400" />
      <data missionId="54" quality="4" weight="20" baseAward="30000_1780035_20,30000_840420_20" advAward="30000_840162_75,30000_1000002_10" baseCondition="1_8000" advCondition="5_1_2_1049,6_1_3101019_1" continueTime="28800" />
      <data missionId="55" quality="3" weight="80" baseAward="30000_1780035_15,30000_840420_15" advAward="30000_840162_50,30000_1000002_4" baseCondition="1_6000" advCondition="5_1_1_1036,6_1_3101063_1" continueTime="14400" />
      <data missionId="56" quality="4" weight="40" baseAward="30000_1780035_20,30000_840420_20" advAward="30000_840162_75,30000_1000002_10" baseCondition="1_8000" advCondition="5_1_3_1036,5_1_1_1048" continueTime="28800" />
      <data missionId="57" quality="1" weight="270" baseAward="30000_1780035_5,30000_840420_5" advAward="30000_840162_15,30000_800109_2" baseCondition="1_2000" advCondition="5_1_1_1007,6_1_3101004_1" continueTime="3600" />
      <data missionId="58" quality="2" weight="240" baseAward="30000_1780035_10,30000_840420_10" advAward="30000_840162_30,30000_1000002_2" baseCondition="1_4000" advCondition="5_1_2_1020,6_1_3101050_1" continueTime="7200" />
      <data missionId="59" quality="3" weight="60" baseAward="30000_1780035_15,30000_840420_15" advAward="30000_840162_50,30000_1000002_4" baseCondition="1_6000" advCondition="5_1_2_1020,5_1_4_1007" continueTime="14400" />
      <data missionId="60" quality="4" weight="30" baseAward="30000_1780035_20,30000_840420_20" advAward="30000_840162_75,30000_1000002_10" baseCondition="1_8000" advCondition="5_1_3_1020,5_1_1_1050" continueTime="28800" />
      <data missionId="61" quality="4" weight="30" baseAward="30000_1780035_20,30000_840420_20" advAward="30000_840162_75,30000_1000002_10" baseCondition="1_8000" advCondition="5_1_4_1002,5_1_1_1044" continueTime="28800" />
      <data missionId="62" quality="4" weight="20" baseAward="30000_1780035_20,30000_840420_20" advAward="30000_840162_75,30000_1000002_10" baseCondition="1_6000" advCondition="5_1_3_1001,5_1_1_1043" continueTime="28800" />
      <data missionId="63" quality="4" weight="15" baseAward="30000_1780035_20,30000_840420_20" advAward="30000_840162_75,30000_1000002_10" baseCondition="1_8000" advCondition="5_1_3_1020,5_1_1_1041" continueTime="28800" />
      <data missionId="64" quality="4" weight="15" baseAward="30000_1780035_20,30000_840420_20" advAward="30000_840162_75,30000_1000002_10" baseCondition="1_8000" advCondition="5_1_3_1018,5_1_1_1046" continueTime="28800" />
      <data missionId="65" quality="4" weight="15" baseAward="30000_1780035_20,30000_840420_20" advAward="30000_840162_75,30000_1000002_10" baseCondition="1_8000" advCondition="5_1_3_1035,5_1_1_1045" continueTime="28800" />
      <data missionId="66" quality="4" weight="20" baseAward="30000_1780035_20,30000_840420_20" advAward="30000_840162_75,30000_1000002_10" baseCondition="3_8000" advCondition="5_1_4_1022,5_1_2_1047" continueTime="28800" />
</root>