<?xml version="1.0" encoding="UTF-8" standalone="yes"?>
<root>
      <data attackTimes="1" damageBonus="2000" />
      <data attackTimes="2" damageBonus="4000" />
      <data attackTimes="3" damageBonus="5500" />
      <data attackTimes="4" damageBonus="6500" />
      <data attackTimes="5" damageBonus="7500" />
      <data attackTimes="6" damageBonus="8000" />
      <data attackTimes="7" damageBonus="8500" />
      <data attackTimes="8" damageBonus="9000" />
      <data attackTimes="9" damageBonus="10000" />
      <data attackTimes="10" damageBonus="10500" />
      <data attackTimes="11" damageBonus="11000" />
      <data attackTimes="12" damageBonus="11500" />
      <data attackTimes="13" damageBonus="12000" />
      <data attackTimes="14" damageBonus="12500" />
      <data attackTimes="15" damageBonus="13000" />
      <data attackTimes="16" damageBonus="13500" />
      <data attackTimes="17" damageBonus="14000" />
      <data attackTimes="18" damageBonus="14500" />
      <data attackTimes="19" damageBonus="15000" />
      <data attackTimes="20" damageBonus="15500" />
      <data attackTimes="21" damageBonus="16000" />
</root>