<?xml version="1.0" encoding="UTF-8" standalone="yes"?>
<root>
      <data id="1" talentId="10001" level="1" type="1" effect="352_200" exp="0" />
      <data id="2" talentId="10002" level="1" type="1" effect="352_300" exp="0" />
      <data id="3" talentId="10003" level="1" type="1" effect="352_400" exp="0" />
      <data id="4" talentId="10004" level="1" type="1" effect="352_500" exp="0" />
      <data id="5" talentId="10005" level="1" type="1" effect="352_600" exp="0" />
      <data id="6" talentId="10006" level="1" type="1" effect="352_700" exp="0" />
      <data id="7" talentId="10007" level="1" type="1" effect="352_800" exp="0" />
      <data id="8" talentId="10008" level="1" type="1" effect="352_900" exp="0" />
      <data id="9" talentId="10009" level="1" type="1" effect="352_1000" exp="0" />
      <data id="10" talentId="10010" level="1" type="1" effect="352_1100" exp="0" />
      <data id="11" talentId="20101" level="1" type="2" effect="352_200" exp="100" />
      <data id="12" talentId="20102" level="2" type="2" effect="352_300" exp="200" />
      <data id="13" talentId="20103" level="3" type="2" effect="352_400" exp="300" />
      <data id="14" talentId="20104" level="4" type="2" effect="352_500" exp="400" />
      <data id="15" talentId="20105" level="5" type="2" effect="352_600" exp="500" />
      <data id="16" talentId="20201" level="1" type="2" effect="352_200" exp="100" />
      <data id="17" talentId="20202" level="2" type="2" effect="352_300" exp="200" />
      <data id="18" talentId="20203" level="3" type="2" effect="352_400" exp="300" />
      <data id="19" talentId="20204" level="4" type="2" effect="352_500" exp="400" />
      <data id="20" talentId="20205" level="5" type="2" effect="352_600" exp="500" />
      <data id="21" talentId="20301" level="1" type="2" effect="352_200" exp="100" />
      <data id="22" talentId="20302" level="2" type="2" effect="352_300" exp="200" />
      <data id="23" talentId="20303" level="3" type="2" effect="352_400" exp="300" />
      <data id="24" talentId="20304" level="4" type="2" effect="352_500" exp="400" />
      <data id="25" talentId="20305" level="5" type="2" effect="352_600" exp="500" />
      <data id="26" talentId="20401" level="1" type="2" effect="352_200" exp="100" />
      <data id="27" talentId="20402" level="2" type="2" effect="352_300" exp="200" />
      <data id="28" talentId="20403" level="3" type="2" effect="352_400" exp="300" />
      <data id="29" talentId="20404" level="4" type="2" effect="352_500" exp="400" />
      <data id="30" talentId="20405" level="5" type="2" effect="352_600" exp="500" />
      <data id="31" talentId="20501" level="1" type="2" effect="352_200" exp="100" />
      <data id="32" talentId="20502" level="2" type="2" effect="352_300" exp="200" />
      <data id="33" talentId="20503" level="3" type="2" effect="352_400" exp="300" />
      <data id="34" talentId="20504" level="4" type="2" effect="352_500" exp="400" />
      <data id="35" talentId="20505" level="5" type="2" effect="352_600" exp="500" />
      <data id="36" talentId="20601" level="1" type="2" effect="352_200" exp="100" />
      <data id="37" talentId="20602" level="2" type="2" effect="352_300" exp="200" />
      <data id="38" talentId="20603" level="3" type="2" effect="352_400" exp="300" />
      <data id="39" talentId="20604" level="4" type="2" effect="352_500" exp="400" />
      <data id="40" talentId="20605" level="5" type="2" effect="352_600" exp="500" />
      <data id="41" talentId="20701" level="1" type="2" effect="352_200" exp="100" />
      <data id="42" talentId="20702" level="2" type="2" effect="352_300" exp="200" />
      <data id="43" talentId="20703" level="3" type="2" effect="352_400" exp="300" />
      <data id="44" talentId="20704" level="4" type="2" effect="352_500" exp="400" />
      <data id="45" talentId="20705" level="5" type="2" effect="352_600" exp="500" />
      <data id="46" talentId="20801" level="1" type="2" effect="352_200" exp="100" />
      <data id="47" talentId="20802" level="2" type="2" effect="352_300" exp="200" />
      <data id="48" talentId="20803" level="3" type="2" effect="352_400" exp="300" />
      <data id="49" talentId="20804" level="4" type="2" effect="352_500" exp="400" />
      <data id="50" talentId="20805" level="5" type="2" effect="352_600" exp="500" />
      <data id="51" talentId="20901" level="1" type="2" effect="352_200" exp="100" />
      <data id="52" talentId="20902" level="2" type="2" effect="352_300" exp="200" />
      <data id="53" talentId="20903" level="3" type="2" effect="352_400" exp="300" />
      <data id="54" talentId="20904" level="4" type="2" effect="352_500" exp="400" />
      <data id="55" talentId="20905" level="5" type="2" effect="352_600" exp="500" />
      <data id="56" talentId="21001" level="1" type="2" effect="352_200" exp="100" />
      <data id="57" talentId="21002" level="2" type="2" effect="352_300" exp="200" />
      <data id="58" talentId="21003" level="3" type="2" effect="352_400" exp="300" />
      <data id="59" talentId="21004" level="4" type="2" effect="352_500" exp="400" />
      <data id="60" talentId="21005" level="5" type="2" effect="352_600" exp="500" />
      <data id="61" talentId="21101" level="1" type="2" effect="352_200" exp="100" />
      <data id="62" talentId="21102" level="2" type="2" effect="352_300" exp="200" />
      <data id="63" talentId="21103" level="3" type="2" effect="352_400" exp="300" />
      <data id="64" talentId="21104" level="4" type="2" effect="352_500" exp="400" />
      <data id="65" talentId="21105" level="5" type="2" effect="352_600" exp="500" />
      <data id="66" talentId="21201" level="1" type="2" effect="352_200" exp="100" />
      <data id="67" talentId="21202" level="2" type="2" effect="352_300" exp="200" />
      <data id="68" talentId="21203" level="3" type="2" effect="352_400" exp="300" />
      <data id="69" talentId="21204" level="4" type="2" effect="352_500" exp="400" />
      <data id="70" talentId="21205" level="5" type="2" effect="352_600" exp="500" />
</root>